setup.cfg
setup.py
rsbhsm/__init__.py
rsbhsm/rsbhsm.py
rsbhsm.egg-info/PKG-INFO
rsbhsm.egg-info/SOURCES.txt
rsbhsm.egg-info/dependency_links.txt
rsbhsm.egg-info/requires.txt
rsbhsm.egg-info/top_level.txt