Metadata-Version: 1.1
Name: rsbhsm
Version: 0.2.0
Summary: An RSB extension for transitions
Home-page: http://github.com/aleneum/rsbhsm
Author: Alexander Neumann
Author-email: aleneum@gmail.com
License: MIT
Download-URL: https://github.com/aleneum/rsbhsm/archive/0.1.0.zip
Platform: UNKNOWN
Classifier: License :: OSI Approved :: MIT License
Classifier: Topic :: Software Development :: Libraries :: Application Frameworks
Classifier: Development Status :: 3 - Alpha
Classifier: Programming Language :: Python :: 2
Classifier: Programming Language :: Python :: 2.7
